inorbit_connector/__init__.py
inorbit_connector/commands.py
inorbit_connector/connector.py
inorbit_connector/models.py
inorbit_connector/utils.py
inorbit_connector/logging/__init__.py
inorbit_connector/logging/formatters.py
inorbit_connector/logging/logger.py
inorbit_connector/logging/logging.default.conf
inorbit_connector-2.2.0.dist-info/licenses/LICENSE
inorbit_connector-2.2.0.dist-info/METADATA
inorbit_connector-2.2.0.dist-info/WHEEL
inorbit_connector-2.2.0.dist-info/top_level.txt
inorbit_connector-2.2.0.dist-info/RECORD
