Metadata-Version: 2.4
Name: inorbit-connector
Version: 2.2.0
Summary: A Python library for connectors in the InOrbit RobOps ecosystem.
Download-URL: https://github.com/inorbit-ai/inorbit-connector-python/archive/refs/tags/v2.2.0.zip
Author-email: "InOrbit, Inc." <support@inorbit.ai>
Maintainer-email: "InOrbit, Inc." <support@inorbit.ai>
License: MIT License
Project-URL: Documentation, https://inorbit-ai.github.io/inorbit-connector-python/
Project-URL: Tracker, https://github.com/inorbit-ai/inorbit-connector-python/issues
Project-URL: Contributing, https://github.com/inorbit-ai/inorbit-connector-python/blob/v2.2.0/CONTRIBUTING.md
Project-URL: Code of Conduct, https://github.com/inorbit-ai/inorbit-connector-python/blob/v2.2.0/CODE_OF_CONDUCT.md
Project-URL: Issue Tracker, https://github.com/inorbit-ai/inorbit-connector-python/issues
Project-URL: License, https://github.com/inorbit-ai/inorbit-connector-python/blob/v2.2.0/LICENSE
Project-URL: About, https://www.inorbit.ai/company
Project-URL: Contact, https://www.inorbit.ai/contact
Project-URL: Blog, https://www.inorbit.ai/blog
Project-URL: Twitter, https://twitter.com/InOrbitAI
Project-URL: LinkedIn, https://www.linkedin.com/company/inorbitai
Project-URL: GitHub, https://github.com/inorbit-ai
Project-URL: Website, https://www.inorbit.ai/
Project-URL: Source, https://github.com/inorbit-ai/inorbit-connector-python/tree/v2.2.0
Keywords: inorbit,robops,robotics
Classifier: Development Status :: 4 - Beta
Classifier: Intended Audience :: Developers
Classifier: Natural Language :: English
Classifier: Operating System :: MacOS :: MacOS X
Classifier: Operating System :: Microsoft :: Windows
Classifier: Operating System :: POSIX :: Linux
Classifier: Programming Language :: Python :: 3.10
Classifier: Programming Language :: Python :: 3.11
Classifier: Programming Language :: Python :: 3.12
Classifier: Programming Language :: Python :: 3.13
Classifier: Topic :: Software Development :: Libraries :: Python Modules
Classifier: License :: OSI Approved :: MIT License
Requires-Python: <3.14,>=3.10
License-File: LICENSE
Requires-Dist: inorbit-edge[video]<3.0,>=2.0
Requires-Dist: pydantic<3.0,>=2.11
Requires-Dist: pytz>=2025.1
Requires-Dist: PyYAML<7.0,>=6.0.2
Requires-Dist: typing_extensions>=4.5.0; python_version < "3.12"
Provides-Extra: dev
Requires-Dist: bump2version~=1.0; extra == "dev"
Requires-Dist: black~=25.9; extra == "dev"
Requires-Dist: coverage~=7.10; extra == "dev"
Requires-Dist: flake8~=7.3; extra == "dev"
Requires-Dist: flake8-pyproject~=1.2; extra == "dev"
Requires-Dist: pytest~=8.4; extra == "dev"
Requires-Dist: pytest-asyncio~=1.2; extra == "dev"
Requires-Dist: setuptools~=80.9; extra == "dev"
Requires-Dist: tox~=4.30; extra == "dev"
Requires-Dist: reuse~=6.2; extra == "dev"
Provides-Extra: docs
Requires-Dist: sphinx~=8.2; extra == "docs"
Requires-Dist: myst-parser; extra == "docs"
Requires-Dist: furo; extra == "docs"
Provides-Extra: colorlog
Requires-Dist: colorlog==6.9.0; extra == "colorlog"
Provides-Extra: system-stats
Requires-Dist: psutil>=7; extra == "system-stats"
Dynamic: download-url
Dynamic: license-file
Dynamic: project-url
